README.rst
setup.cfg
setup.py
http_process_proxy.egg-info/PKG-INFO
http_process_proxy.egg-info/SOURCES.txt
http_process_proxy.egg-info/dependency_links.txt
http_process_proxy.egg-info/entry_points.txt
http_process_proxy.egg-info/requires.txt
http_process_proxy.egg-info/top_level.txt
httpprocessproxy/__init__.py
httpprocessproxy/__main__.py
httpprocessproxy/backend.py
httpprocessproxy/frontend.py
httpprocessproxy/livereload.js
httpprocessproxy/livereload.py
httpprocessproxy/watcher.py