Metadata-Version: 2.1
Name: http-process-proxy
Version: 0.0.10
Summary: HTTP reverse proxy to live-reload a web server
Home-page: https://github.com/CJWorkbench/http-process-proxy
Author: Adam Hooper
Author-email: adam@adamhooper.com
License: MIT
Platform: UNKNOWN
Classifier: Development Status :: 2 - Pre-Alpha
Classifier: Environment :: Console
Classifier: Intended Audience :: Developers
Classifier: Programming Language :: Python :: 3
Classifier: Programming Language :: Python :: 3.7
Classifier: License :: OSI Approved :: MIT License
Classifier: Topic :: Internet :: WWW/HTTP :: HTTP Servers
Classifier: Topic :: Software Development :: Build Tools
Provides-Extra: dev
